cli_FSD/__init__.py
cli_FSD/api_routes.py
cli_FSD/chat_models.py
cli_FSD/command_handlers.py
cli_FSD/command_history.py
cli_FSD/configuration.py
cli_FSD/execution_manager.py
cli_FSD/llm_query_router.py
cli_FSD/main.py
cli_FSD/model_manager.py
cli_FSD/ollama_models.py
cli_FSD/plugin_system.py
cli_FSD/query_router.py
cli_FSD/script_handlers.py
cli_FSD/tool_fallback_manager.py
cli_FSD/utils.py
cli_FSD/version.py
cli_FSD/web_fetcher.py
cli_FSD/web_search.py
cli_FSD/agents/__init__.py
cli_FSD/agents/context_agent.py
cli_FSD/agents/sequential_thinking_agent.py
cli_FSD/agents/web_content_agent.py
cli_FSD/config_files/__init__.py
cli_FSD/config_files/mcp_settings.json
cli_FSD/file_interaction/__init__.py
cli_FSD/file_interaction/example.py
cli_FSD/file_interaction/server.py
cli_FSD/legacy/__init__.py
cli_FSD/linting/__init__.py
cli_FSD/linting/code_checker.py
cli_FSD/linting/formatters.py
cli_FSD/memory/__init__.py
cli_FSD/memory/server.py
cli_FSD/plugins/__init__.py
cli_FSD/plugins/enhanced_web_tool.py
cli_FSD/resources/__init__.py
cli_FSD/resources/assembler.py
cli_FSD/resources/test-ollama.py
cli_FSD/small_context/__init__.py
cli_FSD/small_context/cache.py
cli_FSD/small_context/cli.py
cli_FSD/small_context/integration.py
cli_FSD/small_context/protocol.py
cli_FSD/small_context/server.py
cli_FSD/small_context/test_server.py
cli_FSD/small_context/tests.py
cli_FSD/tests/__init__.py
cli_FSD/tests/test_agent_integration.py
cli_FSD/tests/test_context_agent.py
cli_fsd-2.2.0.dist-info/licenses/LICENSE
cli_fsd-2.2.0.dist-info/METADATA
cli_fsd-2.2.0.dist-info/WHEEL
cli_fsd-2.2.0.dist-info/entry_points.txt
cli_fsd-2.2.0.dist-info/top_level.txt
cli_fsd-2.2.0.dist-info/RECORD
