Metadata-Version: 2.4
Name: cli-FSD
Version: 2.2.0
Summary: LLM-enabled companion utility for your terminal.
Home-page: https://github.com/wazacraft/cli-FSD
Author: JG
Author-email: wazacraftRFID@gmail.com
Classifier: Programming Language :: Python :: 3
Classifier: License :: OSI Approved :: MIT License
Classifier: Operating System :: OS Independent
Requires-Python: >=3.6
License-File: LICENSE
Requires-Dist: Flask
Requires-Dist: flask-cors
Requires-Dist: python-dotenv
Requires-Dist: requests
Requires-Dist: ollama
Requires-Dist: groq
Requires-Dist: beautifulsoup4
Requires-Dist: aiohttp
Requires-Dist: redis
Requires-Dist: pylint
Requires-Dist: beautifulsoup4
Requires-Dist: flake8
Requires-Dist: rich
Requires-Dist: regex
Requires-Dist: aiohttp
Dynamic: author
Dynamic: author-email
Dynamic: classifier
Dynamic: description
Dynamic: description-content-type
Dynamic: home-page
Dynamic: license-file
Dynamic: requires-dist
Dynamic: requires-python
Dynamic: summary
